pyfreekassa/__init__.py
pyfreekassa/pyfreekassa.py
pyfreekassa-1.0.1.dist-info/LICENSE
pyfreekassa-1.0.1.dist-info/METADATA
pyfreekassa-1.0.1.dist-info/WHEEL
pyfreekassa-1.0.1.dist-info/top_level.txt
pyfreekassa-1.0.1.dist-info/RECORD
