Metadata-Version: 2.1
Name: pyfreekassa
Version: 1.0.1
Summary: Python wrapper for FreeKassa api
Home-page: https://github.com/beliboba/pyfreekassa
Author: Beliboba
Author-email: belibobka@gmail.com
Project-URL: Source, https://github.com/beliboba/pyfreekassa
Keywords: freekassa,api,wrapper,client,sdk
Requires-Python: >3.6
License-File: LICENSE
Requires-Dist: aiofiles
Requires-Dist: aiohttp
Requires-Dist: myst-parser
Provides-Extra: docs
Requires-Dist: sphinx ; extra == 'docs'
Requires-Dist: myst-parser ; extra == 'docs'
